[
  { "pkid": "A001", "name": "Nanggroe Aceh Darussalam" },
  { "pkid": "A002", "name": "Sumatera Utara" },
  { "pkid": "A003", "name": "Sumatera Selatan" },
  { "pkid": "A004", "name": "Sumatera Barat" },
  { "pkid": "A005", "name": "Bengkulu" },
  { "pkid": "A006", "name": "Riau" },
  { "pkid": "A007", "name": "Kepulauan Riau" },
  { "pkid": "A008", "name": "Jambi" },
  { "pkid": "A009", "name": "Lampung" },
  { "pkid": "A010", "name": "Bangka Belitung" },
  { "pkid": "A011", "name": "Kalimantan Barat" },
  { "pkid": "A012", "name": "Kalimantan Timur" },
  { "pkid": "A013", "name": "Kalimantan Selatan" },
  { "pkid": "A014", "name": "Kalimantan Tengah" },
  { "pkid": "A015", "name": "Kalimantan Utara" },
  { "pkid": "A016", "name": "Banten" },
  { "pkid": "A017", "name": "DKI Jakarta" },
  { "pkid": "A018", "name": "Jawa Barat" },
  { "pkid": "A019", "name": "Jawa Tengah" },
  { "pkid": "A020", "name": "Daerah Istimewa Yogyakarta" },
  { "pkid": "A021", "name": "Jawa Timur" },
  { "pkid": "A022", "name": "Bali" },
  { "pkid": "A023", "name": "Nusa Tenggara Timur" },
  { "pkid": "A024", "name": "Nusa Tenggara Barat" },
  { "pkid": "A025", "name": "Gorontalo" },
  { "pkid": "A026", "name": "Sulawesi Barat" },
  { "pkid": "A027", "name": "Sulawesi Tengah" },
  { "pkid": "A028", "name": "Sulawesi Utara" },
  { "pkid": "A029", "name": "Sulawesi Tenggara" },
  { "pkid": "A030", "name": "Sulawesi Selatan" },
  { "pkid": "A031", "name": "Maluku Utara" },
  { "pkid": "A032", "name": "Maluku" },
  { "pkid": "A033", "name": "Papua Barat" },
  { "pkid": "A034", "name": "Papua" },
  { "pkid": "A035", "name": "Papua Tengah" },
  { "pkid": "A036", "name": "Papua Pegunungan" },
  { "pkid": "A037", "name": "Papua Selatan" },
  { "pkid": "A038", "name": "Papua Barat Daya" }
]
